bioseba/DNAGPT/.git
bioseba/DNAGPT/.gitignore
bioseba/DNAGPT/LICENSE.txt
bioseba/DNAGPT/README.md
bioseba/DNAGPT/checkpoints/README.md
bioseba/DNAGPT/dna_gpt/__init__.py
bioseba/DNAGPT/dna_gpt/model/__init__.py
bioseba/DNAGPT/dna_gpt/model/dna_gpt.py
bioseba/DNAGPT/dna_gpt/model/gpt.py
bioseba/DNAGPT/dna_gpt/tokenizer.py
bioseba/DNAGPT/dna_gpt/utils.py
bioseba/DNAGPT/requirements.txt
bioseba/DNAGPT/scripts/classification.sh
bioseba/DNAGPT/scripts/generation.sh
bioseba/DNAGPT/scripts/regression.sh
bioseba/DNAGPT/test.py
bioseba/README.md
bioseba/__init__.py
bioseba/adapter_model/README.md
bioseba/adapter_model/adapter_config.json
bioseba/adapter_model/adapter_model.bin
bioseba/generator.py
bioseba/process_finetune_data.py
bioseba/run_finetune.py
bioseba/train_classifier.sh
bioseba/util.py
bioseba-0.1.2.dist-info/METADATA
bioseba-0.1.2.dist-info/WHEEL
bioseba-0.1.2.dist-info/entry_points.txt
bioseba-0.1.2.dist-info/RECORD
