Metadata-Version: 2.1
Name: bioseba
Version: 0.1.2
Summary: 
Author: liminghong.dev
Author-email: lmh0066@outlook.com
Requires-Python: >=3.9,<4.0
Classifier: Programming Language :: Python :: 3
Classifier: Programming Language :: Python :: 3.9
Classifier: Programming Language :: Python :: 3.10
Classifier: Programming Language :: Python :: 3.11
Classifier: Programming Language :: Python :: 3.12
Requires-Dist: click (>=8.1.7,<9.0.0)
Requires-Dist: einops (>=0.7.0,<0.8.0)
Requires-Dist: gdown (>=5.1.0,<6.0.0)
Requires-Dist: pandas (>=2.0,<3.0)
Requires-Dist: peft (>=0.5.0,<0.6.0)
Requires-Dist: transformers (==4.29.2)
Requires-Dist: triton (==2.0.0.dev20221202)
